pyams_content_themes/__init__.py
pyams_content_themes/include.py
pyams_content_themes/interfaces.py
pyams_content_themes/skin.py
pyams_content_themes/locales/pyams_content_themes.pot
pyams_content_themes/locales/fr/LC_MESSAGES/pyams_content_themes.mo
pyams_content_themes/locales/fr/LC_MESSAGES/pyams_content_themes.po
pyams_content_themes/resources/static/assets/clock.png
pyams_content_themes/resources/static/assets/email.png
pyams_content_themes/resources/static/assets/fa-brands-400.ttf
pyams_content_themes/resources/static/assets/fa-brands-400.woff2
pyams_content_themes/resources/static/assets/fa-regular-400.ttf
pyams_content_themes/resources/static/assets/fa-regular-400.woff2
pyams_content_themes/resources/static/assets/fa-solid-900.ttf
pyams_content_themes/resources/static/assets/fa-solid-900.woff2
pyams_content_themes/resources/static/assets/fa-v4compatibility.ttf
pyams_content_themes/resources/static/assets/fa-v4compatibility.woff2
pyams_content_themes/resources/static/assets/form.png
pyams_content_themes/resources/static/assets/fullscreen.png
pyams_content_themes/resources/static/assets/fullscreen@2x.png
pyams_content_themes/resources/static/assets/layers-2x.png
pyams_content_themes/resources/static/assets/layers.png
pyams_content_themes/resources/static/assets/list-item.png
pyams_content_themes/resources/static/assets/map.png
pyams_content_themes/resources/static/assets/marker-icon.png
pyams_content_themes/resources/static/assets/mobile-menu.png
pyams_content_themes/resources/static/assets/phone.png
pyams_content_themes/resources/static/assets/social-icons.png
pyams_content_themes/resources/static/css/dev/pyams-almond.css
pyams_content_themes/resources/static/css/dev/pyams-darkgreen.css
pyams_content_themes/resources/static/css/dev/pyams.css
pyams_content_themes/resources/static/css/dist/pyams-almond.css
pyams_content_themes/resources/static/css/dist/pyams-darkgreen.css
pyams_content_themes/resources/static/css/dist/pyams.css
pyams_content_themes-2.1.1.dist-info/LICENSE
pyams_content_themes-2.1.1.dist-info/METADATA
pyams_content_themes-2.1.1.dist-info/WHEEL
pyams_content_themes-2.1.1.dist-info/entry_points.txt
pyams_content_themes-2.1.1.dist-info/namespace_packages.txt
pyams_content_themes-2.1.1.dist-info/top_level.txt
pyams_content_themes-2.1.1.dist-info/RECORD
