Metadata-Version: 2.1
Name: pyams-content-themes
Version: 2.1.1
Summary: PyAMS sample themes
Home-page: https://pyams.readthedocs.io
Author: Thierry Florac
Author-email: tflorac@ulthar.net
License: ZPL
Keywords: Pyramid PyAMS
Classifier: License :: OSI Approved :: Zope Public License
Classifier: Development Status :: 4 - Beta
Classifier: Programming Language :: Python
Classifier: Framework :: Pyramid
Classifier: Topic :: Software Development :: Libraries :: Python Modules
Requires-Python: >=3.7
License-File: LICENSE
Requires-Dist: setuptools
Requires-Dist: fanstatic
Requires-Dist: pyams-content >=2.7.0
Requires-Dist: pyams-form
Requires-Dist: pyams-layer
Requires-Dist: pyams-portal
Requires-Dist: pyams-skin
Requires-Dist: pyams-template
Requires-Dist: pyramid >=2.0.0
Requires-Dist: importlib-resources ; python_version < "3.9"
Provides-Extra: test
Requires-Dist: pyramid-zcml ; extra == 'test'
Requires-Dist: zope.exceptions ; extra == 'test'
